togglwrapper/__init__.py
togglwrapper/api.py
togglwrapper/decorators.py
togglwrapper/exceptions.py
togglwrapper/mixins.py
togglwrapper-2.0.0.dist-info/LICENSE
togglwrapper-2.0.0.dist-info/METADATA
togglwrapper-2.0.0.dist-info/NOTICE
togglwrapper-2.0.0.dist-info/WHEEL
togglwrapper-2.0.0.dist-info/top_level.txt
togglwrapper-2.0.0.dist-info/RECORD
