Metadata-Version: 2.1
Name: togglwrapper
Version: 2.0.0
Summary: UNKNOWN
Home-page: https://github.com/aarose/togglwrapper
Author: aarose
License: MIT
Keywords: toggl timetracking API wrapper
Platform: UNKNOWN
Classifier: Development Status :: 5 - Production/Stable
Classifier: Intended Audience :: Developers
Classifier: Topic :: Software Development :: Libraries :: Python Modules
Classifier: License :: OSI Approved :: MIT License
Classifier: Natural Language :: English
Classifier: Programming Language :: Python :: 2.7
Classifier: Programming Language :: Python :: 3
Classifier: Programming Language :: Python :: 3.2
Classifier: Programming Language :: Python :: 3.3
Classifier: Programming Language :: Python :: 3.4
License-File: LICENSE
License-File: NOTICE
Requires-Dist: requests
Provides-Extra: dev
Requires-Dist: requests (==2.26.0) ; extra == 'dev'
Requires-Dist: wheel (==0.37.0) ; extra == 'dev'
Requires-Dist: cookies (==2.2.1) ; extra == 'dev'
Requires-Dist: coverage (==5.5) ; extra == 'dev'
Requires-Dist: mock (==4.0.3) ; extra == 'dev'
Requires-Dist: pbr (==5.6.0) ; extra == 'dev'
Requires-Dist: responses (==0.4.0) ; extra == 'dev'
Requires-Dist: six (==1.16.0) ; extra == 'dev'
